{
  "date": "2025-11-10",
  "fetchedAt": "2026-02-05T07:45:53.886Z",
  "articleCount": 131,
  "source": "historical-import",
  "articles": [
    {
      "title": "Trump Media Posts $3.1 Billion in Assets as Digital and Crypto Strategy Scales",
      "link": "NULL",
      "pubDate": "2025-11-10T23:30:44.000Z",
      "source": "Historical",
      "sourceKey": "historical",
      "category": "general",
      "currencies": [
        "CRO"
      ]
    },
    {
      "title": "Uniswap token jumps 38% after fee switch, burn proposal hits the table",
      "link": "NULL",
      "pubDate": "2025-11-10T23:15:49.000Z",
      "source": "Historical",
      "sourceKey": "historical",
      "category": "defi",
      "currencies": [
        "UNI"
      ]
    },
    {
      "title": "ICP Price Prediction: Coinbase Launchpad Speculation Fuels 235% Rally as ICP Breaks Out of Multi-Year Slump",
      "link": "NULL",
      "pubDate": "2025-11-10T23:00:00.000Z",
      "source": "Historical",
      "sourceKey": "historical",
      "category": "trading",
      "currencies": [
        "ICP"
      ]
    },
    {
      "title": "BAND Protocol Integrates With Arc: Is BAND Price Set For Come Back?",
      "link": "NULL",
      "pubDate": "2025-11-10T22:55:48.000Z",
      "source": "Historical",
      "sourceKey": "historical",
      "category": "trading",
      "currencies": [
        "LINK",
        "BAND"
      ]
    },
    {
      "title": "Is Arthur Hayes Rotating His Bitcoin Into ZCash?",
      "link": "NULL",
      "pubDate": "2025-11-10T22:31:08.000Z",
      "source": "Historical",
      "sourceKey": "historical",
      "category": "bitcoin",
      "currencies": [
        "BTC",
        "ZEC"
      ]
    },
    {
      "title": "Perplexity AI Predicts the Price of XRP, Solana, Zcash by the End of 2025",
      "link": "NULL",
      "pubDate": "2025-11-10T22:30:00.000Z",
      "source": "Historical",
      "sourceKey": "historical",
      "category": "trading",
      "currencies": [
        "XRP",
        "SOL",
        "ZEC"
      ]
    },
    {
      "title": "Uniswap Proposes Governance Overhaul to Activate Protocol Fees",
      "link": "NULL",
      "pubDate": "2025-11-10T22:11:30.000Z",
      "source": "Historical",
      "sourceKey": "historical",
      "category": "defi",
      "currencies": [
        "UNI"
      ]
    },
    {
      "title": "UNI token soars 30% as Uniswap Labs and Foundation propose fee switch activation",
      "link": "NULL",
      "pubDate": "2025-11-10T22:06:45.000Z",
      "source": "Historical",
      "sourceKey": "historical",
      "category": "defi",
      "currencies": [
        "UNI",
        "PEOPLE",
        "DEFI"
      ]
    },
    {
      "title": "Dogecoin Price Prediction: DOGE ETF Could Launch in 20 Days – Is Smart Money Quietly Loading Up DOGE?",
      "link": "NULL",
      "pubDate": "2025-11-10T22:01:00.000Z",
      "source": "Historical",
      "sourceKey": "historical",
      "category": "trading",
      "currencies": [
        "DOGE"
      ]
    },
    {
      "title": "HBAR News: HBAR Market Cap Surges Past $8.3B Amid Strong On-Chain Growth",
      "link": "NULL",
      "pubDate": "2025-11-10T22:00:56.000Z",
      "source": "Historical",
      "sourceKey": "historical",
      "category": "trading",
      "currencies": [
        "HBAR"
      ]
    },
    {
      "title": "Privacy Coin Market Booms as Zcash Leads 700% Rally, Binance Handles 78% of Trading Volume",
      "link": "NULL",
      "pubDate": "2025-11-10T21:40:43.000Z",
      "source": "Historical",
      "sourceKey": "historical",
      "category": "trading",
      "currencies": [
        "BTC",
        "ZEC"
      ]
    },
    {
      "title": "Cardano Whales Scoop Up 348M ADA After Sub-$0.50 Dip — Here is What Traders Should Watch",
      "link": "NULL",
      "pubDate": "2025-11-10T21:39:48.000Z",
      "source": "Historical",
      "sourceKey": "historical",
      "category": "altcoin",
      "currencies": [
        "ADA"
      ]
    },
    {
      "title": "Uniswap Launches “UNIfication” Proposal to Activate Fees and Burn Millions of UNI Tokens",
      "link": "NULL",
      "pubDate": "2025-11-10T21:30:49.000Z",
      "source": "Historical",
      "sourceKey": "historical",
      "category": "defi",
      "currencies": [
        "UNI"
      ],
      "votes": {
        "positive": 1,
        "negative": 0
      },
      "sentiment": "bullish"
    },
    {
      "title": "Binance Integrates Trading Bots and USDC Pairs in Latest Market Upgrade",
      "link": "NULL",
      "pubDate": "2025-11-10T21:30:01.000Z",
      "source": "Historical",
      "sourceKey": "historical",
      "category": "exchange",
      "currencies": [
        "USDC",
        "MINA"
      ]
    },
    {
      "title": "UNI Soars as Uniswap Labs and Foundation Propose Fee Switch Activation",
      "link": "NULL",
      "pubDate": "2025-11-10T21:02:59.000Z",
      "source": "Historical",
      "sourceKey": "historical",
      "category": "defi",
      "currencies": [
        "UNI"
      ]
    },
    {
      "title": "Uniswap Proposes Sweeping ‘UNIfication’ With UNI Burn and Protocol Fee Overhaul",
      "link": "NULL",
      "pubDate": "2025-11-10T20:54:20.000Z",
      "source": "Historical",
      "sourceKey": "historical",
      "category": "defi",
      "currencies": [
        "UNI"
      ]
    },
    {
      "title": "Bitcoin, Ethereum, Dogecoin Steady As XRP Surges Amid Government Shutdown Vote",
      "link": "NULL",
      "pubDate": "2025-11-10T20:37:13.000Z",
      "source": "Historical",
      "sourceKey": "historical",
      "category": "bitcoin",
      "currencies": [
        "BTC",
        "ETH",
        "XRP"
      ]
    },
    {
      "title": "Ethereum Price Reclaims $3,600 as BitMine Buys Another 18,271 ETH",
      "link": "NULL",
      "pubDate": "2025-11-10T20:27:56.000Z",
      "source": "Historical",
      "sourceKey": "historical",
      "category": "ethereum",
      "description": "BitMine adds an additional 18,271 Ethereum to its treasury as the market regains momentum and Ethereum’s price surges high.",
      "currencies": [
        "ETH"
      ],
      "votes": {
        "positive": 6,
        "negative": 1
      },
      "sentiment": "bullish"
    },
    {
      "title": "UNI price explodes 14.5%: These TWO key metrics confirm the bullish trend",
      "link": "NULL",
      "pubDate": "2025-11-10T20:00:01.000Z",
      "source": "Historical",
      "sourceKey": "historical",
      "category": "trading",
      "currencies": [
        "UNI"
      ]
    },
    {
      "title": "Eric Trump Says Q4 2025 Will Be ‘Unbelievable For Bitcoin’, Calls $1 Million BTC Price",
      "link": "NULL",
      "pubDate": "2025-11-10T19:57:28.000Z",
      "source": "Historical",
      "sourceKey": "historical",
      "category": "bitcoin",
      "currencies": [
        "BTC",
        "USDT",
        "USDC"
      ]
    },
    {
      "title": "US Court Clears FBI Over Lost Hard Drive Allegedly Holding $345 Million in Bitcoin",
      "link": "NULL",
      "pubDate": "2025-11-10T19:10:10.000Z",
      "source": "Historical",
      "sourceKey": "historical",
      "category": "bitcoin",
      "currencies": [
        "BTC",
        "USDT",
        "USDC"
      ]
    },
    {
      "title": "Retail is back, especially in $ZEC and $DASH Retail trading volume in futures markets for ZEC and DASH has increased, showing FOMO has kicked in on both coins.",
      "link": "NULL",
      "pubDate": "2025-11-10T19:02:53.000Z",
      "source": "Historical",
      "sourceKey": "historical",
      "category": "general",
      "currencies": [
        "ZEC",
        "DASH"
      ]
    },
    {
      "title": "Zcash posted the highest price gain and also dominated futures trading volume: - $ZEC: $20.0B - $DASH: $5.41B - $XMR: $461.85M - $XVG: $403.98M - $SCRT: $228.25M Current trading volumes are blowing past previous privacy coin hype phases.",
      "link": "NULL",
      "pubDate": "2025-11-10T19:01:13.000Z",
      "source": "Historical",
      "sourceKey": "historical",
      "category": "trading",
      "currencies": [
        "ZEC",
        "DASH",
        "XVG"
      ]
    },
    {
      "title": "Privacy Coins are Heating Up Since the Privacy Coin Hype began (Sept 31, 2025): $ZEC: +707% $DASH: +263% $XVG: +44.2% $SCRT: +41% $XMR: +23.7% Here’s what the data reveals",
      "link": "NULL",
      "pubDate": "2025-11-10T19:00:40.000Z",
      "source": "Historical",
      "sourceKey": "historical",
      "category": "general",
      "currencies": [
        "ZEC",
        "DASH",
        "XVG"
      ]
    },
    {
      "title": "Which Projects Are Leading the Ethereum Development Activity Surge?",
      "link": "NULL",
      "pubDate": "2025-11-10T19:00:13.000Z",
      "source": "Historical",
      "sourceKey": "historical",
      "category": "ethereum",
      "currencies": [
        "ETH",
        "LINK",
        "RAD"
      ],
      "votes": {
        "positive": 0,
        "negative": 1
      },
      "sentiment": "bearish"
    },
    {
      "title": "Litecoin Price Prediction: $LTC Gains 20% in a Week, Could the Bull Run Continue?",
      "link": "NULL",
      "pubDate": "2025-11-10T18:53:48.000Z",
      "source": "Historical",
      "sourceKey": "historical",
      "category": "trading",
      "currencies": [
        "LTC"
      ]
    },
    {
      "title": "Chainlink Bounces 5%, But Breakout Falters at $16.50 Resistance",
      "link": "NULL",
      "pubDate": "2025-11-10T18:37:37.000Z",
      "source": "Historical",
      "sourceKey": "historical",
      "category": "general",
      "currencies": [
        "LINK"
      ]
    },
    {
      "title": "HBAR price surges as Hedera joins Google BigQuery for transparent data access",
      "link": "NULL",
      "pubDate": "2025-11-10T18:35:29.000Z",
      "source": "Historical",
      "sourceKey": "historical",
      "category": "trading",
      "currencies": [
        "HBAR",
        "CLOUD"
      ]
    },
    {
      "title": "Coinbase One subscription",
      "link": "NULL",
      "pubDate": "2025-11-10T18:19:51.000Z",
      "source": "Historical",
      "sourceKey": "historical",
      "category": "exchange",
      "currencies": [
        "USDC",
        "COIN"
      ]
    },
    {
      "title": "TRON DAO Brings Blockchain Education to Columbia and Harvard Through TRON Academy",
      "link": "NULL",
      "pubDate": "2025-11-10T18:00:33.000Z",
      "source": "Historical",
      "sourceKey": "historical",
      "category": "general",
      "currencies": [
        "TRX",
        "DAO"
      ]
    },
    {
      "title": "Trump Coin Soars 20% As Dogecoin, Shiba Inu Fail To Keep Up",
      "link": "NULL",
      "pubDate": "2025-11-10T17:45:09.000Z",
      "source": "Historical",
      "sourceKey": "historical",
      "category": "altcoin",
      "currencies": [
        "DOGE",
        "SHIB",
        "TRUMP"
      ]
    },
    {
      "title": "Crypto Price Analysis 11-10: BITCOIN: BTC, ETHEREUM: ETH, SOLANA: SOL, CARDANO: ADA, UNISWAP: UNI",
      "link": "NULL",
      "pubDate": "2025-11-10T17:28:15.000Z",
      "source": "Historical",
      "sourceKey": "historical",
      "category": "bitcoin",
      "currencies": [
        "BTC",
        "ETH",
        "SOL"
      ]
    },
    {
      "title": "Dogecoin Price Prediction: Can Elon Musk’s Resurgence Push $DOGE to $1 in 2025?",
      "link": "NULL",
      "pubDate": "2025-11-10T17:26:09.000Z",
      "source": "Historical",
      "sourceKey": "historical",
      "category": "trading",
      "currencies": [
        "DOGE"
      ]
    },
    {
      "title": "Shiba Inu, Dogecoin Prices To Burst Out With 200% Gains?",
      "link": "NULL",
      "pubDate": "2025-11-10T17:25:00.000Z",
      "source": "Historical",
      "sourceKey": "historical",
      "category": "trading",
      "currencies": [
        "DOGE",
        "SHIB"
      ]
    },
    {
      "title": "Zcash Price Prediction: While Bitcoin Sleeps, Zcash Explodes Higher – Could ZEC Overtake Bitcoin?",
      "link": "NULL",
      "pubDate": "2025-11-10T17:04:59.000Z",
      "source": "Historical",
      "sourceKey": "historical",
      "category": "bitcoin",
      "currencies": [
        "BTC",
        "XMR",
        "ZEC"
      ]
    },
    {
      "title": "Stellar’s XLM Rises 3.6%, Breaking Key Resistance Amid Bullish Signals",
      "link": "NULL",
      "pubDate": "2025-11-10T16:54:12.000Z",
      "source": "Historical",
      "sourceKey": "historical",
      "category": "trading",
      "currencies": [
        "XLM"
      ]
    },
    {
      "title": "HBAR Surge Signals Institutional Momentum Despite Late-Session Pullback",
      "link": "NULL",
      "pubDate": "2025-11-10T16:49:51.000Z",
      "source": "Historical",
      "sourceKey": "historical",
      "category": "trading",
      "currencies": [
        "HBAR"
      ]
    },
    {
      "title": "Coinbase launches public token sales platform with US access, Monad as the first issuer",
      "link": "NULL",
      "pubDate": "2025-11-10T16:49:21.000Z",
      "source": "Historical",
      "sourceKey": "historical",
      "category": "exchange",
      "currencies": [
        "USDC"
      ]
    },
    {
      "title": "ICP Falls 11.2% to $6.69 After Losing Key $7.00 Support",
      "link": "NULL",
      "pubDate": "2025-11-10T16:47:59.000Z",
      "source": "Historical",
      "sourceKey": "historical",
      "category": "general",
      "currencies": [
        "ICP"
      ]
    },
    {
      "title": "Neo News: Week in Review – November 3 – November 9",
      "link": "NULL",
      "pubDate": "2025-11-10T16:25:15.000Z",
      "source": "Historical",
      "sourceKey": "historical",
      "category": "general",
      "currencies": [
        "NEO",
        "FLM",
        "A"
      ]
    },
    {
      "title": "Crypto Majors Surge! US Gov may re-open soon! BTC back above $106k!",
      "link": "NULL",
      "pubDate": "2025-11-10T16:23:35.000Z",
      "source": "Historical",
      "sourceKey": "historical",
      "category": "bitcoin",
      "currencies": [
        "BTC",
        "ETH",
        "BNB"
      ]
    },
    {
      "title": "Litecoin Founder Reveals Major Crypto Shift 14 Years After LTC Creation",
      "link": "NULL",
      "pubDate": "2025-11-10T16:23:00.000Z",
      "source": "Historical",
      "sourceKey": "historical",
      "category": "general",
      "currencies": [
        "LTC"
      ]
    },
    {
      "title": "XRP Ledger Reveals Major Milestone, 'Rich Dad, Poor Dad' Author Drops Epic $250k Bitcoin Price Prediction, Whales Dump Dogecoin (DOGE) — Crypto News Digest",
      "link": "NULL",
      "pubDate": "2025-11-10T16:22:41.000Z",
      "source": "Historical",
      "sourceKey": "historical",
      "category": "bitcoin",
      "currencies": [
        "BTC",
        "XRP",
        "DOGE"
      ]
    },
    {
      "title": "Coinbase Launches Monthly Token Sale Platform, Taps Monad for First $187 Million Offering",
      "link": "NULL",
      "pubDate": "2025-11-10T16:22:19.000Z",
      "source": "Historical",
      "sourceKey": "historical",
      "category": "exchange",
      "currencies": [
        "USDC",
        "MON"
      ]
    },
    {
      "title": "XRP Soars 11% as ETF Speculation Heats Up, Analyst Forecasts Rally to $3.60 Next",
      "link": "NULL",
      "pubDate": "2025-11-10T16:01:59.000Z",
      "source": "Historical",
      "sourceKey": "historical",
      "category": "trading",
      "currencies": [
        "BTC",
        "XRP",
        "SOL"
      ]
    },
    {
      "title": "Dogecoin Price Prediction: Trump’s Dividend Pledge Sparks Dogecoin Price Breakout Above $0.18",
      "link": "NULL",
      "pubDate": "2025-11-10T16:00:56.000Z",
      "source": "Historical",
      "sourceKey": "historical",
      "category": "trading",
      "currencies": [
        "DOGE",
        "PRDT"
      ]
    },
    {
      "title": "Dogecoin Price Could See 4,440% Rally To $5 If This Macro Cycle Repeats",
      "link": "NULL",
      "pubDate": "2025-11-10T16:00:34.000Z",
      "source": "Historical",
      "sourceKey": "historical",
      "category": "trading",
      "currencies": [
        "DOGE",
        "ATH",
        "4"
      ]
    },
    {
      "title": "UNI soars 12% as Uniswap v4’s $200B milestone fuels bullish momentum",
      "link": "NULL",
      "pubDate": "2025-11-10T15:56:16.000Z",
      "source": "Historical",
      "sourceKey": "historical",
      "category": "defi",
      "currencies": [
        "UNI"
      ]
    },
    {
      "title": "Best Crypto Presales to Buy Now as Bitcoin Rebounds to $105K: New Bull Run?",
      "link": "NULL",
      "pubDate": "2025-11-10T15:31:56.000Z",
      "source": "Historical",
      "sourceKey": "historical",
      "category": "bitcoin",
      "currencies": [
        "BTC",
        "SOL",
        "DOGE"
      ]
    },
    {
      "title": "Zcash and World Liberty Financial Lead Top Crypto Gainers: Best Altcoins to Buy Now?",
      "link": "NULL",
      "pubDate": "2025-11-10T15:28:39.000Z",
      "source": "Historical",
      "sourceKey": "historical",
      "category": "general",
      "currencies": [
        "BTC",
        "SOL",
        "ZEC"
      ]
    },
    {
      "title": "Zcash Faces Potential Correction Amid Overbought Conditions",
      "link": "NULL",
      "pubDate": "2025-11-10T15:23:48.000Z",
      "source": "Historical",
      "sourceKey": "historical",
      "category": "general",
      "currencies": [
        "ZEC"
      ]
    },
    {
      "title": "Circle Expands USDC Supply on Ethereum Network",
      "link": "NULL",
      "pubDate": "2025-11-10T15:18:53.000Z",
      "source": "Historical",
      "sourceKey": "historical",
      "category": "ethereum",
      "currencies": [
        "ETH",
        "USDC"
      ]
    },
    {
      "title": "Zcash may see ‘violent end’ as ZEC price rallies 1500% in just two months",
      "link": "NULL",
      "pubDate": "2025-11-10T15:15:17.000Z",
      "source": "Historical",
      "sourceKey": "historical",
      "category": "trading",
      "currencies": [
        "ZEC"
      ]
    },
    {
      "title": "KuCoin Ventures: Prediction Market Growth Signals Infrastructure Opportunity Beyond Platform Hype",
      "link": "NULL",
      "pubDate": "2025-11-10T15:13:23.000Z",
      "source": "Historical",
      "sourceKey": "historical",
      "category": "general",
      "currencies": [
        "KCS"
      ]
    },
    {
      "title": "Cardano breaks 30-day downtrend, but can ADA really go as high as $0.89?",
      "link": "NULL",
      "pubDate": "2025-11-10T15:00:18.000Z",
      "source": "Historical",
      "sourceKey": "historical",
      "category": "altcoin",
      "currencies": [
        "ADA"
      ]
    },
    {
      "title": "Is SHIB targeting a trendline breakout rally? Check forecast",
      "link": "NULL",
      "pubDate": "2025-11-10T15:00:14.000Z",
      "source": "Historical",
      "sourceKey": "historical",
      "category": "trading",
      "currencies": [
        "SHIB",
        "4"
      ]
    },
    {
      "title": "Zcash developer identity debates fuel 1,700% price surge",
      "link": "NULL",
      "pubDate": "2025-11-10T14:54:05.000Z",
      "source": "Historical",
      "sourceKey": "historical",
      "category": "trading",
      "currencies": [
        "ZEC",
        "Z"
      ]
    },
    {
      "title": "USDC Treasury Mints Over 100 Million USDC",
      "link": "NULL",
      "pubDate": "2025-11-10T14:53:44.000Z",
      "source": "Historical",
      "sourceKey": "historical",
      "category": "stablecoin",
      "currencies": [
        "USDC"
      ]
    },
    {
      "title": "BitMine Immersion Expands to 3.5 Million ETH, Growing Crypto Holdings to $13.2 Billion",
      "link": "NULL",
      "pubDate": "2025-11-10T14:49:44.000Z",
      "source": "Historical",
      "sourceKey": "historical",
      "category": "ethereum",
      "description": "BitMine Immersion Technologies (NYSE American: BMNR) has announced that its combined crypto, cash, and “moonshot” investments now total $13. 2 billion, positioning the company as the largest Ethereum holder globally and one of the top two corporate crypto treasuries in the world. According to the company’s latest disclosure, BitMine’s assets include 3,505,723 ETH valued at $3,639 per […] The post BitMine Immersion Expands to 3. 5 Million ETH, Growing Crypto Holdings to $13",
      "currencies": [
        "ETH"
      ],
      "votes": {
        "positive": 5,
        "negative": 2
      },
      "sentiment": "bullish"
    },
    {
      "title": "Coinbase Brings Back Pre-Listing Access For Tokens As COIN Targets $369",
      "link": "NULL",
      "pubDate": "2025-11-10T14:49:02.000Z",
      "source": "Historical",
      "sourceKey": "historical",
      "category": "exchange",
      "currencies": [
        "USDC"
      ]
    },
    {
      "title": "How BTC, DOGE, and ETH Holders Can Earn Daily Rewards with DeepHash (2025 Guide)",
      "link": "NULL",
      "pubDate": "2025-11-10T14:30:00.000Z",
      "source": "Historical",
      "sourceKey": "historical",
      "category": "bitcoin",
      "currencies": [
        "BTC",
        "ETH",
        "DOGE"
      ]
    },
    {
      "title": "HBAR retests $0.20 resistance level amid Hedera price breakout",
      "link": "NULL",
      "pubDate": "2025-11-10T14:29:44.000Z",
      "source": "Historical",
      "sourceKey": "historical",
      "category": "trading",
      "currencies": [
        "HBAR",
        "A"
      ]
    },
    {
      "title": "Debate Over Zcash Developer’s Identity Sparks Rumors They Created Bitcoin",
      "link": "NULL",
      "pubDate": "2025-11-10T14:27:27.000Z",
      "source": "Historical",
      "sourceKey": "historical",
      "category": "bitcoin",
      "currencies": [
        "BTC",
        "ZEC"
      ]
    },
    {
      "title": "Binance 11/11 Update: Two USDC Crypto Pairs in Fresh Listings",
      "link": "NULL",
      "pubDate": "2025-11-10T14:25:00.000Z",
      "source": "Historical",
      "sourceKey": "historical",
      "category": "exchange",
      "currencies": [
        "USDC"
      ]
    },
    {
      "title": "CoinDesk 20 Performance Update: Uniswap (UNI) Surges 16.6% as Nearly All Assets Rise",
      "link": "NULL",
      "pubDate": "2025-11-10T14:21:22.000Z",
      "source": "Historical",
      "sourceKey": "historical",
      "category": "defi",
      "currencies": [
        "UNI"
      ]
    },
    {
      "title": "Crypto Market Soars as Senate Votes to End US Government Shutdown: Best Altcoins to Buy Now",
      "link": "NULL",
      "pubDate": "2025-11-10T14:12:15.000Z",
      "source": "Historical",
      "sourceKey": "historical",
      "category": "general",
      "currencies": [
        "BTC",
        "SOL",
        "ZEC"
      ]
    },
    {
      "title": "Altcoins Coiling for Massive Rally: Ripple (XRP) & Cardano (ADA) Analysis",
      "link": "NULL",
      "pubDate": "2025-11-10T14:02:43.000Z",
      "source": "Historical",
      "sourceKey": "historical",
      "category": "trading",
      "currencies": [
        "BTC",
        "ADA",
        "XRP"
      ]
    },
    {
      "title": "Dogecoin Surges 4%: What's Behind The Rally?",
      "link": "NULL",
      "pubDate": "2025-11-10T13:49:57.000Z",
      "source": "Historical",
      "sourceKey": "historical",
      "category": "trading",
      "currencies": [
        "DOGE",
        "SHIB",
        "PEPE"
      ]
    },
    {
      "title": "Uniswap price forecast as UNI hits 1-month high above $7",
      "link": "NULL",
      "pubDate": "2025-11-10T13:44:22.000Z",
      "source": "Historical",
      "sourceKey": "historical",
      "category": "defi",
      "currencies": [
        "UNI"
      ]
    },
    {
      "title": "Zcash News: Privacy Token Zcash Extends Rally with Halving Days Away",
      "link": "NULL",
      "pubDate": "2025-11-10T13:30:46.000Z",
      "source": "Historical",
      "sourceKey": "historical",
      "category": "bitcoin",
      "currencies": [
        "ZEC"
      ]
    },
    {
      "title": "Shiba Inu's Shibarium Crosses Major On-Chain Milestone to Hit 14 Million Blocks, What's Next?",
      "link": "NULL",
      "pubDate": "2025-11-10T13:23:00.000Z",
      "source": "Historical",
      "sourceKey": "historical",
      "category": "altcoin",
      "currencies": [
        "SHIB"
      ]
    },
    {
      "title": "XRP, XLM in Top Performers Today as Crypto Recovers",
      "link": "NULL",
      "pubDate": "2025-11-10T13:11:00.000Z",
      "source": "Historical",
      "sourceKey": "historical",
      "category": "altcoin",
      "currencies": [
        "XRP",
        "XLM"
      ]
    },
    {
      "title": "Cardano Foundation Reports Strong Progress on Global Adoption Roadmap Across Web3, RWA, and Governance",
      "link": "NULL",
      "pubDate": "2025-11-10T13:00:56.000Z",
      "source": "Historical",
      "sourceKey": "historical",
      "category": "altcoin",
      "currencies": [
        "ADA",
        "RWA"
      ],
      "votes": {
        "positive": 0,
        "negative": 1
      },
      "sentiment": "bearish"
    },
    {
      "title": "Zcash (ZEC) Price Analysis for November 10",
      "link": "NULL",
      "pubDate": "2025-11-10T12:58:00.000Z",
      "source": "Historical",
      "sourceKey": "historical",
      "category": "trading",
      "currencies": [
        "ZEC"
      ]
    },
    {
      "title": "Has Zcash (ZEC) Crossed From Comeback Story to Crypto Bubble?",
      "link": "NULL",
      "pubDate": "2025-11-10T12:36:50.000Z",
      "source": "Historical",
      "sourceKey": "historical",
      "category": "general",
      "currencies": [
        "ZEC"
      ]
    },
    {
      "title": "Crypto funds extend exodus to second week with $1.17B outflows",
      "link": "NULL",
      "pubDate": "2025-11-10T12:33:10.000Z",
      "source": "Historical",
      "sourceKey": "historical",
      "category": "regulation",
      "currencies": [
        "BTC",
        "XRP",
        "SOL"
      ]
    },
    {
      "title": "Cardano News: Analyst Draws Correlation Between ADA and Business Liquidity Cycle",
      "link": "NULL",
      "pubDate": "2025-11-10T12:30:00.000Z",
      "source": "Historical",
      "sourceKey": "historical",
      "category": "defi",
      "currencies": [
        "ADA"
      ]
    },
    {
      "title": "Is Wall Street finally ready for XRP?",
      "link": "NULL",
      "pubDate": "2025-11-10T12:28:26.000Z",
      "source": "Historical",
      "sourceKey": "historical",
      "category": "altcoin",
      "currencies": [
        "XRP",
        "LTC",
        "HBAR"
      ]
    },
    {
      "title": "Shiba Inu Burn Rate Soars 67,557%: Is The Bull Run Back?",
      "link": "NULL",
      "pubDate": "2025-11-10T12:23:53.000Z",
      "source": "Historical",
      "sourceKey": "historical",
      "category": "trading",
      "currencies": [
        "DOGE",
        "SHIB",
        "PEPE"
      ]
    },
    {
      "title": "THORWallet Launches Stellar Cross-Chain Swaps Powered by NEAR Intents",
      "link": "NULL",
      "pubDate": "2025-11-10T12:00:00.000Z",
      "source": "Historical",
      "sourceKey": "historical",
      "category": "general",
      "currencies": [
        "BTC",
        "ETH",
        "BNB"
      ]
    },
    {
      "title": "Stellar Price Forecast: XLM flashes bullish potential as long positions build up",
      "link": "NULL",
      "pubDate": "2025-11-10T11:42:43.000Z",
      "source": "Historical",
      "sourceKey": "historical",
      "category": "trading",
      "currencies": [
        "XLM"
      ]
    },
    {
      "title": "Bitcoin Rallies To $106,000 As Ethereum, XRP, Dogecoin Surge 5% On Senate Shutdown Deal",
      "link": "NULL",
      "pubDate": "2025-11-10T11:37:13.000Z",
      "source": "Historical",
      "sourceKey": "historical",
      "category": "bitcoin",
      "currencies": [
        "BTC",
        "ETH",
        "XRP"
      ]
    },
    {
      "title": "Dogecoin Price Outlook: Could the Next Big Cycle Be Starting?",
      "link": "NULL",
      "pubDate": "2025-11-10T11:34:00.000Z",
      "source": "Historical",
      "sourceKey": "historical",
      "category": "trading",
      "currencies": [
        "DOGE"
      ]
    },
    {
      "title": "Litecoin reclaims $100 as ‘overlooked workhorse’ LTC looks to shine",
      "link": "NULL",
      "pubDate": "2025-11-10T11:30:31.000Z",
      "source": "Historical",
      "sourceKey": "historical",
      "category": "general",
      "currencies": [
        "BTC",
        "LTC"
      ]
    },
    {
      "title": "Dogecoin targets $0.22 as risk-on sentiment returns; Check forecast",
      "link": "NULL",
      "pubDate": "2025-11-10T11:11:16.000Z",
      "source": "Historical",
      "sourceKey": "historical",
      "category": "altcoin",
      "currencies": [
        "BTC",
        "DOGE"
      ]
    },
    {
      "title": "Bank of England opens consultation on ‘systemic’ GBP stablecoin rules with temporary holding limits",
      "link": "NULL",
      "pubDate": "2025-11-10T11:01:45.000Z",
      "source": "Historical",
      "sourceKey": "historical",
      "category": "regulation",
      "currencies": [
        "USDT",
        "USDC"
      ]
    },
    {
      "title": "UNI token rallies on expectation of fee sharing",
      "link": "NULL",
      "pubDate": "2025-11-10T10:37:27.000Z",
      "source": "Historical",
      "sourceKey": "historical",
      "category": "general",
      "currencies": [
        "UNI"
      ]
    },
    {
      "title": "Nothing Can Officially Represent Dogecoin, Developer Tells Community",
      "link": "NULL",
      "pubDate": "2025-11-10T10:28:00.000Z",
      "source": "Historical",
      "sourceKey": "historical",
      "category": "altcoin",
      "currencies": [
        "DOGE"
      ]
    },
    {
      "title": "7 Low-Cap Presales Under $1 to Buy Before They Explode",
      "link": "NULL",
      "pubDate": "2025-11-10T09:42:16.000Z",
      "source": "Historical",
      "sourceKey": "historical",
      "category": "general",
      "currencies": [
        "SHIB",
        "A"
      ]
    },
    {
      "title": "Cardano Price Prediction – What Could Make ADA Take Off Soon?",
      "link": "NULL",
      "pubDate": "2025-11-10T09:39:48.000Z",
      "source": "Historical",
      "sourceKey": "historical",
      "category": "trading",
      "currencies": [
        "ADA"
      ]
    },
    {
      "title": "Best Dogecoin Cloud Mining Platforms in 2025: Top 8 Regulated Crypto Mining Sites to Earn DOGE Safely and Effortlessly",
      "link": "NULL",
      "pubDate": "2025-11-10T09:24:47.000Z",
      "source": "Historical",
      "sourceKey": "historical",
      "category": "altcoin",
      "currencies": [
        "DOGE"
      ]
    },
    {
      "title": "Neo Core Developers discuss dynamic block intervals, post-quantum cryptography, and Neo 3.9 features in recent meeting",
      "link": "NULL",
      "pubDate": "2025-11-10T09:15:30.000Z",
      "source": "Historical",
      "sourceKey": "historical",
      "category": "general",
      "currencies": [
        "NEO",
        "A"
      ]
    },
    {
      "title": "This New DeFi Crypto Could Explode 18900% to Outshine Shiba Inu (SHIB) Potential",
      "link": "NULL",
      "pubDate": "2025-11-10T09:08:50.000Z",
      "source": "Historical",
      "sourceKey": "historical",
      "category": "defi",
      "currencies": [
        "SHIB"
      ]
    },
    {
      "title": "Filecoin Rises 2%, Support at $2.63 Level Broken",
      "link": "NULL",
      "pubDate": "2025-11-10T09:08:50.000Z",
      "source": "Historical",
      "sourceKey": "historical",
      "category": "general",
      "currencies": [
        "FIL"
      ]
    },
    {
      "title": "Trump May Have Promised Tariff Dividend Of $2,000 To Each American, But Crypto Bettors Doubt It'll Happen This Year",
      "link": "NULL",
      "pubDate": "2025-11-10T08:49:57.000Z",
      "source": "Historical",
      "sourceKey": "historical",
      "category": "general",
      "currencies": [
        "BTC",
        "USDC",
        "ZEC"
      ]
    },
    {
      "title": "3 Token Unlocks to Watch in the Second Week of November 2025",
      "link": "NULL",
      "pubDate": "2025-11-10T08:48:35.000Z",
      "source": "Historical",
      "sourceKey": "historical",
      "category": "regulation",
      "currencies": [
        "AVAX",
        "APT",
        "LINEA"
      ]
    },
    {
      "title": "Privacy Coin Wars: Snowden’s Zcash Endorsement Sparks Monero Community Backlash",
      "link": "NULL",
      "pubDate": "2025-11-10T08:45:16.000Z",
      "source": "Historical",
      "sourceKey": "historical",
      "category": "general",
      "currencies": [
        "XMR",
        "ZEC"
      ]
    },
    {
      "title": "Best Crypto To Buy Now: Prices Skyrocket As Senate Votes To Reopen US Government",
      "link": "NULL",
      "pubDate": "2025-11-10T08:41:03.000Z",
      "source": "Historical",
      "sourceKey": "historical",
      "category": "trading",
      "currencies": [
        "BTC",
        "ETH",
        "XRP"
      ]
    },
    {
      "title": "Crypto Markets Turn Green as Political Stability Returns to Washington",
      "link": "NULL",
      "pubDate": "2025-11-10T08:40:43.000Z",
      "source": "Historical",
      "sourceKey": "historical",
      "category": "general",
      "currencies": [
        "BTC",
        "ETH",
        "XRP"
      ]
    },
    {
      "title": "Low-Cap Privacy Play: Why Capital is Rotating From ZEC and DASH Into COTI",
      "link": "NULL",
      "pubDate": "2025-11-10T08:24:50.000Z",
      "source": "Historical",
      "sourceKey": "historical",
      "category": "general",
      "currencies": [
        "ZEC",
        "DASH",
        "COTI"
      ]
    },
    {
      "title": "Zcash ZEC crypto: D1 Technical Outlook, Bias & Key Pivots",
      "link": "NULL",
      "pubDate": "2025-11-10T08:14:50.000Z",
      "source": "Historical",
      "sourceKey": "historical",
      "category": "general",
      "currencies": [
        "ZEC"
      ]
    },
    {
      "title": "Zcash Price Forecast: ZEC bulls eye $750 as Open Interest hits record $1.13 billion",
      "link": "NULL",
      "pubDate": "2025-11-10T08:10:15.000Z",
      "source": "Historical",
      "sourceKey": "historical",
      "category": "trading",
      "currencies": [
        "ZEC"
      ]
    },
    {
      "title": "Shiba Inu (SHIB) Price Removed Cursed Zero: Only up From Here?",
      "link": "NULL",
      "pubDate": "2025-11-10T08:06:00.000Z",
      "source": "Historical",
      "sourceKey": "historical",
      "category": "trading",
      "currencies": [
        "SHIB"
      ]
    },
    {
      "title": "All about Filecoin’s wobble after 56% surge and how it can recover",
      "link": "NULL",
      "pubDate": "2025-11-10T08:00:46.000Z",
      "source": "Historical",
      "sourceKey": "historical",
      "category": "trading",
      "currencies": [
        "FIL",
        "A"
      ]
    },
    {
      "title": "What’s Next for ETH, XRP, ADA, SOL as Trump Dangles a $2K ‘Tariff Dividend’",
      "link": "NULL",
      "pubDate": "2025-11-10T07:58:49.000Z",
      "source": "Historical",
      "sourceKey": "historical",
      "category": "ethereum",
      "currencies": [
        "ETH",
        "XRP",
        "SOL"
      ]
    },
    {
      "title": "Elon Musk Discusses DOGE's Impact on Bureaucratic Institutions",
      "link": "NULL",
      "pubDate": "2025-11-10T07:53:02.000Z",
      "source": "Historical",
      "sourceKey": "historical",
      "category": "altcoin",
      "currencies": [
        "DOGE"
      ]
    },
    {
      "title": "Binance to Launch USDC Flexible Products with Up to 5.6% APR",
      "link": "NULL",
      "pubDate": "2025-11-10T07:52:42.000Z",
      "source": "Historical",
      "sourceKey": "historical",
      "category": "exchange",
      "currencies": [
        "USDC",
        "APR"
      ]
    },
    {
      "title": "NEAR Protocol's Ecosystem Boosted by Near Intents Platform",
      "link": "NULL",
      "pubDate": "2025-11-10T07:51:48.000Z",
      "source": "Historical",
      "sourceKey": "historical",
      "category": "general",
      "currencies": [
        "NEAR",
        "4"
      ]
    },
    {
      "title": "Top 5 Altcoins with Important Events Worth Noting This Week: ADA, INJ, LINK, LDO, and XRP",
      "link": "NULL",
      "pubDate": "2025-11-10T07:50:10.000Z",
      "source": "Historical",
      "sourceKey": "historical",
      "category": "altcoin",
      "currencies": [
        "ADA",
        "XRP",
        "LINK"
      ]
    },
    {
      "title": "Web3 Robotics Firm Proposes Acquisition of 1X Technologies Shares",
      "link": "NULL",
      "pubDate": "2025-11-10T07:49:16.000Z",
      "source": "Historical",
      "sourceKey": "historical",
      "category": "general",
      "currencies": [
        "USDC",
        "NEO",
        "DAO"
      ]
    },
    {
      "title": "NEAR Protocol's Near Intents Sees Significant Growth in 2025",
      "link": "NULL",
      "pubDate": "2025-11-10T07:48:42.000Z",
      "source": "Historical",
      "sourceKey": "historical",
      "category": "general",
      "currencies": [
        "NEAR",
        "4"
      ]
    },
    {
      "title": "Zcash Price Rebounds as Open Interest Tops $1B",
      "link": "NULL",
      "pubDate": "2025-11-10T07:34:17.000Z",
      "source": "Historical",
      "sourceKey": "historical",
      "category": "trading",
      "currencies": [
        "ZEC"
      ]
    },
    {
      "title": "theTRONreport Deep Dive – Infra, Rumble, Tether, Ecosystem Value",
      "link": "NULL",
      "pubDate": "2025-11-10T07:16:14.000Z",
      "source": "Historical",
      "sourceKey": "historical",
      "category": "ethereum",
      "currencies": [
        "TRX",
        "WTRX"
      ]
    },
    {
      "title": "Hedara Price Prediction: Analysts Are Backing HBAR Over Ripple and Cardano, But What About Remittix?",
      "link": "NULL",
      "pubDate": "2025-11-10T07:00:00.000Z",
      "source": "Historical",
      "sourceKey": "historical",
      "category": "trading",
      "currencies": [
        "ADA",
        "HBAR"
      ]
    },
    {
      "title": "Dogecoin Price Set For 1,200% Rally To $2.2 In This 3rd Run",
      "link": "NULL",
      "pubDate": "2025-11-10T07:00:00.000Z",
      "source": "Historical",
      "sourceKey": "historical",
      "category": "trading",
      "currencies": [
        "DOGE"
      ]
    },
    {
      "title": "Zcash Privacy Meets Solana DeFi with Zenrock’s Wrapped ZEC Crossing $15M in Volume",
      "link": "NULL",
      "pubDate": "2025-11-10T06:58:14.000Z",
      "source": "Historical",
      "sourceKey": "historical",
      "category": "defi",
      "currencies": [
        "SOL",
        "ZEC"
      ]
    },
    {
      "title": "TRON Daily Report: November 10, 2025 Money Loop Alpha, Contract Traces, and Whale Sniper Plays",
      "link": "NULL",
      "pubDate": "2025-11-10T06:03:31.000Z",
      "source": "Historical",
      "sourceKey": "historical",
      "category": "stablecoin",
      "currencies": [
        "TRX",
        "WTRX"
      ]
    },
    {
      "title": "Litecoin’s price reclaims $100 after on-chain volume hits record highs – Details!",
      "link": "NULL",
      "pubDate": "2025-11-10T06:00:41.000Z",
      "source": "Historical",
      "sourceKey": "historical",
      "category": "trading",
      "currencies": [
        "LTC"
      ]
    },
    {
      "title": "Cardano Price Forecast: ADA shows signs of recovery as whales accumulate and bullish momentum builds",
      "link": "NULL",
      "pubDate": "2025-11-10T05:54:55.000Z",
      "source": "Historical",
      "sourceKey": "historical",
      "category": "trading",
      "currencies": [
        "ADA"
      ]
    },
    {
      "title": "Meme Coins Price Prediction: Dogecoin, Shiba Inu, Pepe rally as risk-on sentiment wakes",
      "link": "NULL",
      "pubDate": "2025-11-10T05:47:14.000Z",
      "source": "Historical",
      "sourceKey": "historical",
      "category": "trading",
      "currencies": [
        "DOGE",
        "SHIB",
        "PEPE"
      ]
    },
    {
      "title": "Dogecoin Surges 6% as Trump Promised $2K Stimulus Brings Back 2021-Era DOGE, SHIB Rally Vibes",
      "link": "NULL",
      "pubDate": "2025-11-10T05:24:01.000Z",
      "source": "Historical",
      "sourceKey": "historical",
      "category": "trading",
      "currencies": [
        "DOGE",
        "SHIB"
      ]
    },
    {
      "title": "Dogecoin Price: Dogecoin’s Elliott Wave Signals $1 – $2 Surge Ahead",
      "link": "NULL",
      "pubDate": "2025-11-10T05:00:33.000Z",
      "source": "Historical",
      "sourceKey": "historical",
      "category": "trading",
      "currencies": [
        "DOGE",
        "RLY"
      ]
    },
    {
      "title": "Is AVAX set for an 18% drop? Short bets, whales, and more…",
      "link": "NULL",
      "pubDate": "2025-11-10T05:00:02.000Z",
      "source": "Historical",
      "sourceKey": "historical",
      "category": "general",
      "currencies": [
        "AVAX"
      ]
    },
    {
      "title": "What Are Crypto Whales Positioning For Amid the Rebound?",
      "link": "NULL",
      "pubDate": "2025-11-10T04:59:45.000Z",
      "source": "Historical",
      "sourceKey": "historical",
      "category": "general",
      "currencies": [
        "BTC",
        "ETH",
        "LINK"
      ]
    },
    {
      "title": "XRP Outgains Bitcoin, Dogecoin With 9% Rally — Move To $10 Coming Soon?",
      "link": "NULL",
      "pubDate": "2025-11-10T04:18:26.000Z",
      "source": "Historical",
      "sourceKey": "historical",
      "category": "bitcoin",
      "currencies": [
        "BTC",
        "XRP",
        "DOGE"
      ]
    },
    {
      "title": "Market Prediction: Cardano’s Hoskinson Predicts 2026 as ‘Beast Year’ for Crypto",
      "link": "NULL",
      "pubDate": "2025-11-10T04:15:45.000Z",
      "source": "Historical",
      "sourceKey": "historical",
      "category": "altcoin",
      "currencies": [
        "ADA"
      ]
    },
    {
      "title": "Monero Surges 20% as Privacy Coin Rotation Intensifies",
      "link": "NULL",
      "pubDate": "2025-11-10T03:12:37.000Z",
      "source": "Historical",
      "sourceKey": "historical",
      "category": "trading",
      "currencies": [
        "XMR",
        "ZEC"
      ]
    },
    {
      "title": "Bitcoin, Ethereum, Dogecoin, XRP Jump On Hopes Government Shutdown Will End: Arthur Hayes Predicts BTC '2 Da Moon' As 'Printing Money' Begins Again",
      "link": "NULL",
      "pubDate": "2025-11-10T01:58:28.000Z",
      "source": "Historical",
      "sourceKey": "historical",
      "category": "bitcoin",
      "currencies": [
        "BTC",
        "ETH",
        "XRP"
      ]
    },
    {
      "title": "AAVE slips to $200: Watch THESE two support levels before any rebound",
      "link": "NULL",
      "pubDate": "2025-11-10T01:00:21.000Z",
      "source": "Historical",
      "sourceKey": "historical",
      "category": "defi",
      "currencies": [
        "AAVE"
      ]
    },
    {
      "title": "Bitcoin (BTC) Loses $100,000, Ripple Holders Refuse to Sell, Franklin Templeton’s XRP ETF to Get Approval, DOGE Risks Adding Zero – Top Weekly Crypto News",
      "link": "NULL",
      "pubDate": "2025-11-10T00:40:01.000Z",
      "source": "Historical",
      "sourceKey": "historical",
      "category": "bitcoin",
      "currencies": [
        "BTC",
        "XRP",
        "DOGE"
      ]
    },
    {
      "title": "Crypto Market Prediction: XRP Has No Chances Here, Shiba Inu (SHIB) Bulls Woke Up With 2.7 Trillion, Bitcoin (BTC) Price's Spooky Tendency",
      "link": "NULL",
      "pubDate": "2025-11-10T00:01:00.000Z",
      "source": "Historical",
      "sourceKey": "historical",
      "category": "bitcoin",
      "currencies": [
        "BTC",
        "XRP",
        "SHIB"
      ]
    }
  ]
}