{
  "date": "2021-11-11",
  "fetchedAt": "2026-02-05T07:45:51.846Z",
  "articleCount": 84,
  "source": "historical-import",
  "articles": [
    {
      "title": "A quick update from @P4Cap and @RVT5000 on #V3 and some changes coming to the #Telcoin app",
      "link": "NULL",
      "pubDate": "2021-11-11T23:13:05.000Z",
      "source": "Historical",
      "sourceKey": "historical",
      "category": "general",
      "currencies": [
        "TEL"
      ]
    },
    {
      "title": "Shiba Inu Continues To Dominate Community-Wise, But Why Is The Price Suffering?",
      "link": "https://bitcoinist.com/shiba-inu-continues-to-dominate-community-wise-but-why-is-the-price-suffering/?utm_source=rss&utm_medium=rss&utm_campaign=shiba-inu-continues-to-dominate-community-wise-but-why-is-the-price-suffering",
      "pubDate": "2021-11-11T23:00:39.000Z",
      "source": "Historical",
      "sourceKey": "historical",
      "category": "trading",
      "description": "Shiba Inu is still popular among the dog coins community. This has not helped in the way of the value as the meme coin has been on a downtrend since the month began. From its all-time high, it has fallen almost 50% to the point where it is now trailing around $0.00005. There isn’t much […]",
      "currencies": [
        "SHIB"
      ],
      "votes": {
        "positive": 6,
        "negative": 2
      },
      "sentiment": "bullish"
    },
    {
      "title": "What Went On In The Secret Meetings Between Cardano Developer IOHK And Zanzibar Officials?",
      "link": "https://www.newsbtc.com/news/cardano/what-went-on-in-the-secret-meetings-between-cardano-developer-iohk-and-zanzibar-officials/",
      "pubDate": "2021-11-11T23:00:14.000Z",
      "source": "Historical",
      "sourceKey": "historical",
      "category": "regulation",
      "description": "The Cardano Africa tour had been in full gear for a couple of weeks now, ending when Hoskinson had returned back to the States. Founder Charles Hoskinson had announced the tour after the successful launch of smart contracts capability on the blockchain and last month, the tour had kicked off. Hoskinson and the Cardano Foundation plan to meet and liaise with developers of Cardano-based projects...",
      "currencies": [
        "USDT",
        "ADA",
        "DOGE"
      ],
      "votes": {
        "positive": 4,
        "negative": 1
      },
      "sentiment": "bullish"
    },
    {
      "title": "We have partnered with the Hive blockchain project! #hive #partnership #blockchain…",
      "link": "NULL",
      "pubDate": "2021-11-11T22:20:26.000Z",
      "source": "Historical",
      "sourceKey": "historical",
      "category": "general",
      "currencies": [
        "SCR"
      ]
    },
    {
      "title": "We wanna know... what first comes to mind when you hear #web3? 🤔",
      "link": "NULL",
      "pubDate": "2021-11-11T22:01:58.000Z",
      "source": "Historical",
      "sourceKey": "historical",
      "category": "general",
      "currencies": [
        "GLM"
      ]
    },
    {
      "title": "In March, @Greet_OS proposed an Escrow solution for Aragon Court. We are excited to announce that the first Escrow…",
      "link": "NULL",
      "pubDate": "2021-11-11T22:00:05.000Z",
      "source": "Historical",
      "sourceKey": "historical",
      "category": "altcoin",
      "currencies": [
        "ANT"
      ]
    },
    {
      "title": "Have you heard about $TITAN? I've got in early in June. I even posted on my blog @mcuban. Waiting to reach $1 again…",
      "link": "NULL",
      "pubDate": "2021-11-11T21:11:47.000Z",
      "source": "Historical",
      "sourceKey": "historical",
      "category": "regulation",
      "currencies": [
        "TITAN"
      ]
    },
    {
      "title": "Ethereum Whale ‘Gimli’ Accumulates Additional 31 Billion Shiba Inu (SHIB) Tokens",
      "link": "https://www.cryptoglobe.com/latest/2021/11/ethereum-whale-gimli-accumulates-additional-31-billion-shiba-inu-shib-tokens/",
      "pubDate": "2021-11-11T20:50:00.000Z",
      "source": "Historical",
      "sourceKey": "historical",
      "category": "ethereum",
      "description": "A mysterious Ethereum ($ETH) whale known as “Gimli” has kept on accumulating the meme-inspired cryptocurrency Shiba Inu ($SHIB) by adding $1.7 million more to his portfolio, now worth over $47 million. The Ethereum whale’s move was first spotted by WhaleStates, which noted the 31.3 billion SHIB tokens the whale purchased were then worth around $1.73 […]",
      "currencies": [
        "ETH",
        "SHIB"
      ],
      "votes": {
        "positive": 14,
        "negative": 3
      },
      "sentiment": "bullish"
    },
    {
      "title": "RT @FROGANON3: @CryptoMessiah $KOK is the best. @KultOfKek",
      "link": "NULL",
      "pubDate": "2021-11-11T20:42:10.000Z",
      "source": "Historical",
      "sourceKey": "historical",
      "category": "general",
      "currencies": [
        "KOK"
      ]
    },
    {
      "title": "RT @KultOfKek: @DYOR_100X We, as the $KOK family, would love to have new initiates among our ranks. Vosit and join…",
      "link": "NULL",
      "pubDate": "2021-11-11T20:42:06.000Z",
      "source": "Historical",
      "sourceKey": "historical",
      "category": "general",
      "currencies": [
        "KOK"
      ]
    },
    {
      "title": "RT @binamonok: For all the holdes of NFT Genesis, we are preparing together our friends from @bakery_swap a new stake from NFT Genesis!! ht…",
      "link": "NULL",
      "pubDate": "2021-11-11T20:30:45.000Z",
      "source": "Historical",
      "sourceKey": "historical",
      "category": "ethereum",
      "currencies": [
        "BAKE"
      ]
    },
    {
      "title": "Shiba Inu (SHIB) Shines in Sea of Red",
      "link": "https://u.today/shiba-inu-shib-shines-in-sea-of-red",
      "pubDate": "2021-11-11T20:08:31.000Z",
      "source": "Historical",
      "sourceKey": "historical",
      "category": "altcoin",
      "description": "The meme coin is holding strong amid a market correction",
      "currencies": [
        "SHIB"
      ],
      "votes": {
        "positive": 8,
        "negative": 6
      }
    },
    {
      "title": "Your first @ is buying you a StormX Membership this Xmas",
      "link": "NULL",
      "pubDate": "2021-11-11T20:00:03.000Z",
      "source": "Historical",
      "sourceKey": "historical",
      "category": "general",
      "currencies": [
        "STMX"
      ]
    },
    {
      "title": "An Unrealized Capital Gains Tax Would Wallop Big Stock And Bitcoin Investors",
      "link": "https://bitcoinmagazine.com/business/unrealized-capital-gains-tax-stock-bitcoin",
      "pubDate": "2021-11-11T20:00:00.000Z",
      "source": "Historical",
      "sourceKey": "historical",
      "category": "bitcoin",
      "description": "If an unrealized capital gains tax is enacted, it could have major ramifications for the economy and create a dangerous precedent.",
      "currencies": [
        "BTC"
      ],
      "votes": {
        "positive": 2,
        "negative": 3
      }
    },
    {
      "title": "The @MiamiCryptoExp show is going great! The #qtum team has been non-stop busy. We've met with a lot of community m…",
      "link": "NULL",
      "pubDate": "2021-11-11T19:43:36.000Z",
      "source": "Historical",
      "sourceKey": "historical",
      "category": "general",
      "currencies": [
        "QTUM"
      ]
    },
    {
      "title": "80k users and counting, when should we add a zero? $XPR ️ #Proton",
      "link": "NULL",
      "pubDate": "2021-11-11T19:38:08.000Z",
      "source": "Historical",
      "sourceKey": "historical",
      "category": "general",
      "currencies": [
        "XPR"
      ]
    },
    {
      "title": "Theta Network is excited to welcome Fuse Media @fusetv as our latest branded media partner, bringing their top tale…",
      "link": "NULL",
      "pubDate": "2021-11-11T19:34:22.000Z",
      "source": "Historical",
      "sourceKey": "historical",
      "category": "general",
      "currencies": [
        "THETA",
        "TFUEL"
      ]
    },
    {
      "title": "Big Doge Dash updates and alpha drops in this interview, from the man himself @CaslinPaul",
      "link": "NULL",
      "pubDate": "2021-11-11T19:31:50.000Z",
      "source": "Historical",
      "sourceKey": "historical",
      "category": "altcoin",
      "currencies": [
        "DASH",
        "DOGEDASH"
      ]
    },
    {
      "title": "RT @MintClubPro: We’re thrilled to announce the acceptance of #MintClub to the Binance Incubation Program season 3. More details will be po…",
      "link": "NULL",
      "pubDate": "2021-11-11T19:16:03.000Z",
      "source": "Historical",
      "sourceKey": "historical",
      "category": "exchange",
      "currencies": [
        "HUNT"
      ]
    },
    {
      "title": "We are now live!!!",
      "link": "NULL",
      "pubDate": "2021-11-11T19:01:21.000Z",
      "source": "Historical",
      "sourceKey": "historical",
      "category": "general",
      "currencies": [
        "SHFL",
        "CARDS"
      ]
    },
    {
      "title": "RT @SecrtPineapple: The Pineapples are just the beginning... We are excited to be working with @Theta_Network and to be one of the first…",
      "link": "NULL",
      "pubDate": "2021-11-11T18:58:41.000Z",
      "source": "Historical",
      "sourceKey": "historical",
      "category": "regulation",
      "currencies": [
        "THETA",
        "TFUEL"
      ]
    },
    {
      "title": "An overview of incentive mechanisms &amp; DAO tooling: Featuring: @poapxyz @rabbithole_gg…",
      "link": "NULL",
      "pubDate": "2021-11-11T18:08:30.000Z",
      "source": "Historical",
      "sourceKey": "historical",
      "category": "general",
      "currencies": [
        "ANT"
      ]
    },
    {
      "title": "Looking forward to watching our Head of Ecosystem Development, and a community leader, @XinfinUSA, speak as well!",
      "link": "NULL",
      "pubDate": "2021-11-11T18:06:53.000Z",
      "source": "Historical",
      "sourceKey": "historical",
      "category": "general",
      "currencies": [
        "XDC"
      ]
    },
    {
      "title": "Big congratulations to @acumenofficial, a @BellaProtocol portfolio and partner, to team up with the #ElSalvador gov…",
      "link": "NULL",
      "pubDate": "2021-11-11T17:28:22.000Z",
      "source": "Historical",
      "sourceKey": "historical",
      "category": "general",
      "currencies": [
        "BEL"
      ]
    },
    {
      "title": "Excited to share the news about our partnership with the Government of Costa Rica to use our blockchain to support…",
      "link": "NULL",
      "pubDate": "2021-11-11T17:23:41.000Z",
      "source": "Historical",
      "sourceKey": "historical",
      "category": "general",
      "currencies": [
        "XCH"
      ]
    },
    {
      "title": "RT @zbruceli: Two major applications built on @NKN_ORG are coming this holiday season, both by community developer team or independent soft…",
      "link": "NULL",
      "pubDate": "2021-11-11T17:14:50.000Z",
      "source": "Historical",
      "sourceKey": "historical",
      "category": "general",
      "currencies": [
        "NKN"
      ]
    },
    {
      "title": "RT @CurveFinance: EUR/USD pools on Ethereum just got some CRV",
      "link": "NULL",
      "pubDate": "2021-11-11T16:55:27.000Z",
      "source": "Historical",
      "sourceKey": "historical",
      "category": "ethereum",
      "currencies": [
        "CRV",
        "EURS"
      ]
    },
    {
      "title": "Dog Coin Shiba Inu Looks to Resume Its Uptrend",
      "link": "https://cryptobriefing.com/dog-coin-shiba-inu-looks-to-resume-its-uptrend/?utm_source=main_feed&utm_medium=rss",
      "pubDate": "2021-11-11T16:41:39.000Z",
      "source": "Historical",
      "sourceKey": "historical",
      "category": "altcoin",
      "currencies": [
        "SHIB"
      ],
      "votes": {
        "positive": 17,
        "negative": 5
      },
      "sentiment": "bullish"
    },
    {
      "title": "Bitcoin Maximalism – Crypto Survivors and OG’s Could Make a Case to Differ",
      "link": "NULL",
      "pubDate": "2021-11-11T16:38:55.000Z",
      "source": "Historical",
      "sourceKey": "historical",
      "category": "bitcoin",
      "currencies": [
        "BTC",
        "ETH",
        "USDT",
        "ADA",
        "XRP",
        "NEAR",
        "XTZ",
        "QTUM"
      ]
    },
    {
      "title": "Hedera Hashgraph (HBAR) Looking to Reach Highest Ever Weekly Close",
      "link": "https://beincrypto.com/hedera-hashgraph-hbar-looking-to-reach-highest-ever-weekly-close/",
      "pubDate": "2021-11-11T16:38:00.000Z",
      "source": "Historical",
      "sourceKey": "historical",
      "category": "general",
      "description": "HBAR is in the process of breaking out from both a diagonal and a horizontal resistance area. Technical indicators support this breakout.",
      "currencies": [
        "HBAR"
      ],
      "votes": {
        "positive": 9,
        "negative": 0
      },
      "sentiment": "bullish"
    },
    {
      "title": "RT @CryptoCrocoFR: OMG I won the lottery 🤯 So happy, I was right to believe in this project but I didn´t thought I would won tjmhe lottery…",
      "link": "NULL",
      "pubDate": "2021-11-11T16:25:52.000Z",
      "source": "Historical",
      "sourceKey": "historical",
      "category": "general",
      "currencies": [
        "OMG"
      ]
    },
    {
      "title": "#Symbol's Cyprus has landed. Land ho!",
      "link": "NULL",
      "pubDate": "2021-11-11T16:25:51.000Z",
      "source": "Historical",
      "sourceKey": "historical",
      "category": "general",
      "currencies": [
        "XEM",
        "XYM"
      ],
      "votes": {
        "positive": 1,
        "negative": 0
      },
      "sentiment": "bullish"
    },
    {
      "title": "🤑🤑Meme contest of Nole!! 1 000 000 NPC 1° reward 🤑🤑",
      "link": "NULL",
      "pubDate": "2021-11-11T16:06:38.000Z",
      "source": "Historical",
      "sourceKey": "historical",
      "category": "general",
      "currencies": [
        "NPC"
      ]
    },
    {
      "title": "In case some of you missed it, you can rewatch our latest AMA over at our YouTube channel",
      "link": "NULL",
      "pubDate": "2021-11-11T16:00:16.000Z",
      "source": "Historical",
      "sourceKey": "historical",
      "category": "general",
      "currencies": [
        "STMX"
      ]
    },
    {
      "title": "Together with @SwapSpaceCo we are starting a giveaway! Complete the following steps for your chance to win 250000 X…",
      "link": "NULL",
      "pubDate": "2021-11-11T15:59:33.000Z",
      "source": "Historical",
      "sourceKey": "historical",
      "category": "ethereum",
      "currencies": [
        "XEC"
      ]
    },
    {
      "title": "Polkadot Parachain Auctions Start Today: What You Need to Know",
      "link": "https://cryptopotato.com/polkadot-parachain-auctions-start-today-what-you-need-to-know/",
      "pubDate": "2021-11-11T15:55:13.000Z",
      "source": "Historical",
      "sourceKey": "historical",
      "category": "general",
      "description": "Polkadot Parachain auctions are an integral part of the network. Here's what you need to know about them.",
      "currencies": [
        "DOT"
      ],
      "votes": {
        "positive": 12,
        "negative": 0
      },
      "sentiment": "bullish"
    },
    {
      "title": "SHIB has discovered a ‘crucial resistance to break,’ says prominent crypto analyst",
      "link": "https://finbold.com/shib-has-discovered-a-crucial-resistance-to-break-says-prominent-crypto-analyst/",
      "pubDate": "2021-11-11T15:54:31.000Z",
      "source": "Historical",
      "sourceKey": "historical",
      "category": "general",
      "description": "Shiba Inu (SHIB) meme currency has rebounded after a week of high volatility and is presently trading in the green... Continue reading",
      "currencies": [
        "SHIB"
      ],
      "votes": {
        "positive": 29,
        "negative": 9
      },
      "sentiment": "bullish"
    },
    {
      "title": "RT @CoinDesk: Cryptocurrency broker @InvestVoyager said it has seen a sharp increase in funded accounts on its platform, hitting 1 million…",
      "link": "NULL",
      "pubDate": "2021-11-11T15:28:59.000Z",
      "source": "Historical",
      "sourceKey": "historical",
      "category": "general",
      "currencies": [
        "VGX"
      ]
    },
    {
      "title": "RT @BitcoinMagazine: Legendary investor Stanley Druckenmiller: USD will lose world reserve currency status.",
      "link": "NULL",
      "pubDate": "2021-11-11T15:14:10.000Z",
      "source": "Historical",
      "sourceKey": "historical",
      "category": "bitcoin",
      "currencies": [
        "TITAN"
      ]
    },
    {
      "title": "Join Nicolas, David, and Rami now for our Q&amp;A session",
      "link": "NULL",
      "pubDate": "2021-11-11T15:05:21.000Z",
      "source": "Historical",
      "sourceKey": "historical",
      "category": "general",
      "currencies": [
        "UOS"
      ]
    },
    {
      "title": "\"Dogecoin Killer\" Shiba Inu to Be Listed on App of India's First Crypto Unicorn",
      "link": "https://u.today/dogecoin-killer-shiba-inu-to-be-listed-on-app-of-indias-first-crypto-unicorn",
      "pubDate": "2021-11-11T14:43:13.000Z",
      "source": "Historical",
      "sourceKey": "historical",
      "category": "altcoin",
      "description": "CoinDCX has announced that Shiba Inu will be available on its retail-friendly app later this week",
      "currencies": [
        "SHIB"
      ],
      "votes": {
        "positive": 26,
        "negative": 6
      },
      "sentiment": "bullish"
    },
    {
      "title": "Find out why, the NFT-gaming company, @TheSandboxGame chose @requestdapps to streamline payments and accounting in…",
      "link": "NULL",
      "pubDate": "2021-11-11T14:39:48.000Z",
      "source": "Historical",
      "sourceKey": "historical",
      "category": "nft",
      "currencies": [
        "REQ"
      ]
    },
    {
      "title": "Solve the problems caused by printing money, by printing more money. 🤯",
      "link": "NULL",
      "pubDate": "2021-11-11T14:33:15.000Z",
      "source": "Historical",
      "sourceKey": "historical",
      "category": "altcoin",
      "currencies": [
        "TITAN"
      ]
    },
    {
      "title": "Shiba Inu Token ($SHIB) ‘Ready To Break Out’, Says Crypto Analyst Ali Martinez",
      "link": "https://www.cryptoglobe.com/latest/2021/11/shiba-inu-token-shib-ready-to-break-out-says-crypto-analyst-ali-martinez/",
      "pubDate": "2021-11-11T14:31:23.000Z",
      "source": "Historical",
      "sourceKey": "historical",
      "category": "altcoin",
      "description": "On Thursday (November 11), a day when 43 of the top 50 cryptoassets (by market cap) are in the red (suffering losses vs USD), highly popular dog meme-based cryptocurrency Shiba Inu ($SHIB) is bucking the trend by going up nearly 8% in the past 24 hours. In fact, $SHIB is one of only three cryptoassets […]",
      "currencies": [
        "SHIB"
      ],
      "votes": {
        "positive": 42,
        "negative": 14
      },
      "sentiment": "bullish"
    },
    {
      "title": "Citadel CEO: Ethereum Is Superior to Bitcoin And Will Eventually Replace it",
      "link": "https://cryptopotato.com/citadel-ceo-ethereum-is-superior-to-bitcoin-and-will-eventually-replace-it/",
      "pubDate": "2021-11-11T14:29:06.000Z",
      "source": "Historical",
      "sourceKey": "historical",
      "category": "bitcoin",
      "description": "According to Ken Griffin, bitcoin has some serious disadvantages that can lead to other cryptocurrencies taking its first spot in the space.",
      "currencies": [
        "BTC",
        "ETH"
      ],
      "votes": {
        "positive": 4,
        "negative": 4
      }
    },
    {
      "title": "Musk Loses DOGE Market Cap in One Day, 51% SHIB Supply Holder Revealed, BTC Whale Turns $249K into $150 Million: Crypto News Digest by U.Today",
      "link": "https://u.today/musk-loses-doge-market-cap-in-one-day-51-shib-supply-holder-revealed-btc-whale-turns-249k-into-150",
      "pubDate": "2021-11-11T14:10:00.000Z",
      "source": "Historical",
      "sourceKey": "historical",
      "category": "bitcoin",
      "description": "U.Today’s news digest keeps you updated on the latest events in the crypto industry",
      "currencies": [
        "BTC",
        "DOGE",
        "SHIB"
      ],
      "votes": {
        "positive": 18,
        "negative": 6
      },
      "sentiment": "bullish"
    },
    {
      "title": "IOTA Standardization Update November 2021",
      "link": "NULL",
      "pubDate": "2021-11-11T14:01:59.000Z",
      "source": "Historical",
      "sourceKey": "historical",
      "category": "general",
      "currencies": [
        "MIOTA",
        "OMG"
      ],
      "votes": {
        "positive": 1,
        "negative": 0
      },
      "sentiment": "bullish"
    },
    {
      "title": "Bitcoin Looks Set to Dip After Traders Lose $700M in Liquidations",
      "link": "https://cryptobriefing.com/bitcoin-set-dip-after-traders-lose-700m-liquidations/?utm_source=main_feed&utm_medium=rss",
      "pubDate": "2021-11-11T13:56:46.000Z",
      "source": "Historical",
      "sourceKey": "historical",
      "category": "bitcoin",
      "currencies": [
        "BTC"
      ],
      "votes": {
        "positive": 3,
        "negative": 3
      }
    },
    {
      "title": "Indonesia’s Islam Council Bans Muslims From Trading Bitcoin, Deems Crypto As “Haram”",
      "link": "https://zycrypto.com/indonesias-islam-council-bans-muslims-from-trading-bitcoin-deems-crypto-as-haram/",
      "pubDate": "2021-11-11T13:54:23.000Z",
      "source": "Historical",
      "sourceKey": "historical",
      "category": "bitcoin",
      "description": "Indonesia’s council of Islam religious leaders has called on Muslims in the country to desist from engaging in crypto-related transactions, terming it as “haram”. According to a Thursday report by Bloomberg, Asronun Niam Sholeh, chair of religious decrees at the National Ulema Council (MUI) decried cryptocurrencies, terming them as “uncertain, wagering and harmful” pitting them against […]",
      "currencies": [
        "BTC"
      ],
      "votes": {
        "positive": 1,
        "negative": 3
      },
      "sentiment": "bearish"
    },
    {
      "title": "OMG guess what  Only 25 boxes to get a guarantee slot in 1st DarePlay's IGO !!! Slots are running out soon…",
      "link": "NULL",
      "pubDate": "2021-11-11T13:31:02.000Z",
      "source": "Historical",
      "sourceKey": "historical",
      "category": "general",
      "currencies": [
        "OMG"
      ]
    },
    {
      "title": "RT @RequestNetwork: Find out why, the NFT-gaming company, @thesandbox chose @requestdapps to streamline payments and accounting in crypto.…",
      "link": "NULL",
      "pubDate": "2021-11-11T12:56:36.000Z",
      "source": "Historical",
      "sourceKey": "historical",
      "category": "nft",
      "currencies": [
        "REQ"
      ]
    },
    {
      "title": "Shiba Inu Price Analysis: SHIB at a Critical Point Following 5% Daily Loss",
      "link": "https://cryptopotato.com/shiba-inu-price-analysis-shib-at-a-critical-point-following-5-daily-loss/",
      "pubDate": "2021-11-11T12:34:12.000Z",
      "source": "Historical",
      "sourceKey": "historical",
      "category": "trading",
      "description": "SHIB price nearly touched the support yesterday during the broad market pullback and has since returned just under the descending triangle's resistance.",
      "currencies": [
        "SHIB"
      ],
      "votes": {
        "positive": 15,
        "negative": 9
      }
    },
    {
      "title": "ATTN: This is your Captain speaking! Cyprus is scheduled to land in approximately 510 blocks. It’s a cool-270.56℃ o…",
      "link": "NULL",
      "pubDate": "2021-11-11T12:06:12.000Z",
      "source": "Historical",
      "sourceKey": "historical",
      "category": "general",
      "currencies": [
        "XEM",
        "XYM"
      ]
    },
    {
      "title": "RT @ZB_Futures: #ZBFutures perpetual swap Is Now Live!",
      "link": "NULL",
      "pubDate": "2021-11-11T11:56:13.000Z",
      "source": "Historical",
      "sourceKey": "historical",
      "category": "general",
      "currencies": [
        "ZB"
      ]
    },
    {
      "title": "RT @nunet_global:  Qualified for the AGIX or SDAO holding requirements for the NuNet Community Contribution round as per the snapshot on…",
      "link": "NULL",
      "pubDate": "2021-11-11T11:49:43.000Z",
      "source": "Historical",
      "sourceKey": "historical",
      "category": "general",
      "currencies": [
        "AGIX"
      ]
    },
    {
      "title": "Don’t tell anyone how profitable, fun and awesome Ravencoin is to mine. If you do everyone will mine it.",
      "link": "NULL",
      "pubDate": "2021-11-11T11:41:18.000Z",
      "source": "Historical",
      "sourceKey": "historical",
      "category": "general",
      "currencies": [
        "RVN"
      ]
    },
    {
      "title": "Crypto community bets Bitcoin to trade at $53,000 by the end of December",
      "link": "https://finbold.com/crypto-community-bets-bitcoin-to-trade-at-53000-by-the-end-of-december/",
      "pubDate": "2021-11-11T11:40:35.000Z",
      "source": "Historical",
      "sourceKey": "historical",
      "category": "bitcoin",
      "description": "The price of Bitcoin (BTC) is expected to trade around $53,000 by the end of December, according to the latest... Continue reading",
      "currencies": [
        "BTC"
      ],
      "votes": {
        "positive": 19,
        "negative": 35
      }
    },
    {
      "title": "RT @RVNfixesWallSt: More adoption every day...! $RVN @Ravencoin #RVN",
      "link": "NULL",
      "pubDate": "2021-11-11T11:40:00.000Z",
      "source": "Historical",
      "sourceKey": "historical",
      "category": "general",
      "currencies": [
        "RVN"
      ]
    },
    {
      "title": "Ravencoin works for NFTs and securities not because it added those features because of a recent fad but because the…",
      "link": "NULL",
      "pubDate": "2021-11-11T11:37:00.000Z",
      "source": "Historical",
      "sourceKey": "historical",
      "category": "nft",
      "currencies": [
        "RVN"
      ]
    },
    {
      "title": "Ripple Unveils Plans For Groundbreaking ‘Liquidity Hub’ To Give Business Customers Seamless Access To Bitcoin, Ether, XRP",
      "link": "https://zycrypto.com/ripple-unveils-plans-for-groundbreaking-liquidity-hub-to-give-business-customers-seamless-access-to-bitcoin-ether-xrp/",
      "pubDate": "2021-11-11T11:26:21.000Z",
      "source": "Historical",
      "sourceKey": "historical",
      "category": "bitcoin",
      "description": "In a surprising twist of events, Ripple has announced plans to launch a “Liquidity Hub” as it targets to offer enterprises direct exposure to digital assets from the broader crypto market beginning in 2022. According to a Tuesday release, the San Francisco-based firm said that the hub will “unleash the potential to access deep liquidity […]",
      "currencies": [
        "BTC",
        "ETH",
        "XRP"
      ],
      "votes": {
        "positive": 12,
        "negative": 1
      },
      "sentiment": "bullish"
    },
    {
      "title": "RT @msjemmagreen: @ScottMorrisonMP Scomo - once you have shaken off the jetlag from Glasgow, lets meet and discuss the technology we have r…",
      "link": "NULL",
      "pubDate": "2021-11-11T10:46:51.000Z",
      "source": "Historical",
      "sourceKey": "historical",
      "category": "general",
      "currencies": [
        "POWR"
      ]
    },
    {
      "title": "RT @protonnz: A Proton wallet update (1.1.18) has just been released for iOS users experiencing issues. #Proton $XPR ️",
      "link": "NULL",
      "pubDate": "2021-11-11T10:44:52.000Z",
      "source": "Historical",
      "sourceKey": "historical",
      "category": "general",
      "currencies": [
        "XPR"
      ]
    },
    {
      "title": "$140 Million XRP Moved Between Wallets While Someone Purchases 14 Million Coins from Binance",
      "link": "https://u.today/140-million-xrp-moved-between-wallets-while-someone-purchases-14-million-coins-from-binance",
      "pubDate": "2021-11-11T10:44:46.000Z",
      "source": "Historical",
      "sourceKey": "historical",
      "category": "altcoin",
      "description": "XRP whales once again moving coins between wallets with large buy happening in the background",
      "currencies": [
        "XRP"
      ],
      "votes": {
        "positive": 8,
        "negative": 0
      },
      "sentiment": "bullish"
    },
    {
      "title": "Xfinite (XET) Partners with Yieldly for a New Staking Pool",
      "link": "https://www.newsbtc.com/news/company/xfinite-xet-partners-with-yieldly-for-a-new-staking-pool/",
      "pubDate": "2021-11-11T10:33:54.000Z",
      "source": "Historical",
      "sourceKey": "historical",
      "category": "defi",
      "description": "Xfinity’s ecosystem utility token, XET, is one of the four largest Algorand Standard Assets (ASAs) to launch the new staking pool partnership with the DeFi platform Yieldly on the 17th of November. The multi-asset pools also include other outstanding projects powered by Algorand: Smile Coin Network (SMILE), the Asia Reserve Currency Coin (ARCC) from the International Blockchain Monetary...",
      "currencies": [
        "ALGO"
      ],
      "votes": {
        "positive": 3,
        "negative": 0
      },
      "sentiment": "bullish"
    },
    {
      "title": "Analyst Predicts One Altcoin Will Rally Ahead of the Pack, Says Bitcoin Pullbacks Likely To Be Shallow",
      "link": "https://dailyhodl.com/2021/11/11/analyst-predicts-one-altcoin-will-rally-ahead-of-the-pack-says-bitcoin-pullbacks-likely-to-be-shallow/",
      "pubDate": "2021-11-11T10:15:48.000Z",
      "source": "Historical",
      "sourceKey": "historical",
      "category": "bitcoin",
      "description": "A closely followed crypto market trader thinks the Bitcoin (BTC) bull market remains in full swing while predicting an early altseason for one crypto asset in particular. The pseudonymous trader known as Altcoin Sherpa is bullish on the decentralized streaming platform Theta (THETA). He tells his 145,900 Twitter followers that THETA may be gearing up […]",
      "currencies": [
        "BTC",
        "ALGO",
        "THETA"
      ],
      "votes": {
        "positive": 7,
        "negative": 0
      },
      "sentiment": "bullish"
    },
    {
      "title": "Nigerian banks tracking customer accounts for crypto trading",
      "link": "https://cointelegraph.com/news/nigerian-banks-tracking-customer-accounts-for-crypto-trading",
      "pubDate": "2021-11-11T09:39:17.000Z",
      "source": "Historical",
      "sourceKey": "historical",
      "category": "regulation",
      "description": "Personal accounts with large multi-day inflow and outflow are being tracked at the behest of the country’s central bank.",
      "currencies": [
        "BTC"
      ],
      "votes": {
        "positive": 0,
        "negative": 6
      },
      "sentiment": "bearish"
    },
    {
      "title": "“Heroism doesn’t always happen in a burst of glory  Sometimes small triumphs and large hearts change the course of…",
      "link": "NULL",
      "pubDate": "2021-11-11T09:36:08.000Z",
      "source": "Historical",
      "sourceKey": "historical",
      "category": "general",
      "currencies": [
        "UQC"
      ]
    },
    {
      "title": "It's official! #ZB has launched the #Futures function. Join ZB and learn Futures trading using the Demo function.",
      "link": "NULL",
      "pubDate": "2021-11-11T09:01:35.000Z",
      "source": "Historical",
      "sourceKey": "historical",
      "category": "general",
      "currencies": [
        "ZB"
      ]
    },
    {
      "title": "JASMY finally unveiled the Secure PC, with official release of the product line and pricing-Car recorder for PC, th…",
      "link": "NULL",
      "pubDate": "2021-11-11T08:52:28.000Z",
      "source": "Historical",
      "sourceKey": "historical",
      "category": "regulation",
      "currencies": [
        "JASMY"
      ]
    },
    {
      "title": "On Engineering with Rosie, @msjemmagreen explains how Powerledger's blockchain technology enables trust in the emer…",
      "link": "NULL",
      "pubDate": "2021-11-11T08:50:01.000Z",
      "source": "Historical",
      "sourceKey": "historical",
      "category": "general",
      "currencies": [
        "POWR"
      ]
    },
    {
      "title": "RT @coingecko: Which #crypto are you currently holding? Why?",
      "link": "NULL",
      "pubDate": "2021-11-11T08:37:37.000Z",
      "source": "Historical",
      "sourceKey": "historical",
      "category": "general",
      "currencies": [
        "CBG"
      ]
    },
    {
      "title": "RT @XTexchange:  will list $BAKE @bakery_swap $KP3R @thekeep3r $SRM @ProjectSerum in the Innovation Zone under BAKE…",
      "link": "NULL",
      "pubDate": "2021-11-11T08:05:52.000Z",
      "source": "Historical",
      "sourceKey": "historical",
      "category": "exchange",
      "currencies": [
        "BAKE"
      ]
    },
    {
      "title": "Ethereum Network Fees Surge to Insane Levels as ENS Hits ATH",
      "link": "https://cryptopotato.com/ethereum-network-fees-surge-to-insane-levels-as-ens-hits-ath/",
      "pubDate": "2021-11-11T07:59:09.000Z",
      "source": "Historical",
      "sourceKey": "historical",
      "category": "ethereum",
      "description": "The cost of using the Ethereum network has surged to its second-highest level ever and the hype over the ENS airdrop may be driving it higher.",
      "currencies": [
        "ETH"
      ],
      "votes": {
        "positive": 6,
        "negative": 9
      }
    },
    {
      "title": "Ripple to launch ‘game-changer’ liquidity hub amid XRP legal battles with SEC",
      "link": "https://forkast.news/ripple-launch-liquidity-hub-amid-xrp-lawsuit-sec/",
      "pubDate": "2021-11-11T07:34:00.000Z",
      "source": "Historical",
      "sourceKey": "historical",
      "category": "defi",
      "description": "Trying to move beyond XRP, Ripple hopes its customers will join RippleNet with a wallet that supports fiat and other cryptos like Bitcoin and Ether.",
      "currencies": [
        "BTC",
        "XRP"
      ],
      "votes": {
        "positive": 44,
        "negative": 2
      },
      "sentiment": "bullish"
    },
    {
      "title": "RT @FUNCTIONX_IO: #FunctionX Foundation President @DavidBenKay spoke in #Fintech and #Cybersecurity Panel with Prof Yang Xiang from @Swinbu…",
      "link": "NULL",
      "pubDate": "2021-11-11T07:06:50.000Z",
      "source": "Historical",
      "sourceKey": "historical",
      "category": "regulation",
      "currencies": [
        "PUNDIX"
      ]
    },
    {
      "title": "New listing! @UpbitThailand list the #PUNDIX-#BTC trading pair. Detail",
      "link": "NULL",
      "pubDate": "2021-11-11T05:56:01.000Z",
      "source": "Historical",
      "sourceKey": "historical",
      "category": "bitcoin",
      "currencies": [
        "PUNDIX"
      ]
    },
    {
      "title": "🤗We understand your frustration, love and patience would be kindly appreciated! Let's build the community together!…",
      "link": "https://twitter.com/BitTorrent/status/1458660761753079811",
      "pubDate": "2021-11-11T05:00:00.000Z",
      "source": "Historical",
      "sourceKey": "historical",
      "category": "ethereum",
      "currencies": [
        "BTT"
      ],
      "votes": {
        "positive": 3,
        "negative": 0
      },
      "sentiment": "bullish"
    },
    {
      "title": "Wallet Accounts on #BitTorrent Speed exceeded 289,000,000！ #BitTorrent Speed aims to incentivize more users to…",
      "link": "NULL",
      "pubDate": "2021-11-11T03:16:05.000Z",
      "source": "Historical",
      "sourceKey": "historical",
      "category": "general",
      "currencies": [
        "BTT",
        "BTTOLD"
      ],
      "votes": {
        "positive": 3,
        "negative": 0
      },
      "sentiment": "bullish"
    },
    {
      "title": "UNSTOPPABLE Kadena, LoopRing Price Rally! CHZ Burn, Harmony ONE, Cartesi",
      "link": "NULL",
      "pubDate": "2021-11-11T02:39:00.000Z",
      "source": "Historical",
      "sourceKey": "historical",
      "category": "trading",
      "description": "LoopRing is PUMPING HARD, but still waiting on those GameStop rumours, Kadena looks UNSTOPPABLE, Harmony is growing on PolyDex, Cartesi's Noether Node draws in RockX, Reddit and Solana invest $100 MILLION!! Mastercard brings fiat and crypto together, TomoChain has a HUGE AIRDROP you cannot miss, CoreStarter is ready for liftoff on TrustPad, Chiliz takes on quarterly burn, and Scotty Beam partners with OMNI, CHECK IT OUT! ⏱️TIMESTAMPS 0:00 Major Headlines 0:35 Introduction 1:18 LoopRing TO THE MO",
      "currencies": [
        "CHZ",
        "LRC",
        "ONE"
      ],
      "votes": {
        "positive": 3,
        "negative": 0
      },
      "sentiment": "bullish"
    },
    {
      "title": "Reason why Glitzkoin GTN moved from $0.20 to $0.75+ in less than 8 weeks? #glitzkoinprice #gtnprice #glitzkoin #gtn",
      "link": "NULL",
      "pubDate": "2021-11-11T02:31:57.000Z",
      "source": "Historical",
      "sourceKey": "historical",
      "category": "trading",
      "currencies": [
        "GTN"
      ]
    },
    {
      "title": "With other 90% support, Cyprus will be landing in T-Minus 14 hours! Upgrade your #Symbol nodes and get ready to emb…",
      "link": "NULL",
      "pubDate": "2021-11-11T02:13:31.000Z",
      "source": "Historical",
      "sourceKey": "historical",
      "category": "general",
      "currencies": [
        "XEM",
        "XYM"
      ]
    },
    {
      "title": "Loopring ($LRC) Outperformed Shiba Inu ($SHIB) and $DOGE Over Last 30 Days. Analysts Say It’s Not Done",
      "link": "https://www.cryptoglobe.com/latest/2021/11/loopring-lrc-outperformed-shiba-inu-shib-and-doge-over-last-30-days-analysts-say-its-not-done/",
      "pubDate": "2021-11-11T01:20:00.000Z",
      "source": "Historical",
      "sourceKey": "historical",
      "category": "altcoin",
      "description": "Loopring ($LRC) has greatly outperformed top meme-inspired cryptocurrencies like Shiba Inu ($SHIB) and Dogecoin ($DOGE) over the last 30 days, and according to some analysts it may not be done moving upward. As Benzinga reported, LRC is a layer-two scaling solution for the Ethereum network meant to facilitate trading and payments. It’s up over 790% […]",
      "currencies": [
        "ETH",
        "DOGE",
        "SHIB"
      ],
      "votes": {
        "positive": 10,
        "negative": 0
      },
      "sentiment": "bullish"
    },
    {
      "title": "RT @moonstake: #NFTs are booming, especially on #CENNZnet with blockbuster projects like @FLUF_World. Moonstake is working hard to support…",
      "link": "NULL",
      "pubDate": "2021-11-11T01:02:24.000Z",
      "source": "Historical",
      "sourceKey": "historical",
      "category": "nft",
      "currencies": [
        "CENNZ"
      ]
    },
    {
      "title": "How to join a DAO? Spoiler alert: it's super easy!",
      "link": "NULL",
      "pubDate": "2021-11-11T01:00:14.000Z",
      "source": "Historical",
      "sourceKey": "historical",
      "category": "general",
      "currencies": [
        "ANT"
      ]
    }
  ]
}