{
  "date": "2018-11-28",
  "fetchedAt": "2026-02-05T07:45:52.025Z",
  "articleCount": 2,
  "source": "historical-import",
  "articles": [
    {
      "title": "Tron [TRX] Top Performer Among the Top 20 Cryptocurrencies Today",
      "link": "NULL",
      "pubDate": "2018-11-28T16:39:49.000Z",
      "source": "Historical",
      "sourceKey": "historical",
      "category": "general",
      "currencies": [
        "TRX"
      ],
      "votes": {
        "positive": 10,
        "negative": 0
      },
      "sentiment": "bullish"
    },
    {
      "title": "Infographic: How crypto news generates fake Ripple hype",
      "link": "NULL",
      "pubDate": "2018-11-28T14:14:21.000Z",
      "source": "Historical",
      "sourceKey": "historical",
      "category": "altcoin",
      "currencies": [
        "XRP"
      ],
      "votes": {
        "positive": 2,
        "negative": 4
      }
    }
  ]
}