{
  "date": "2019-11-15",
  "fetchedAt": "2026-02-05T07:45:51.910Z",
  "articleCount": 5,
  "source": "historical-import",
  "articles": [
    {
      "title": "Weiss Ratings Sparks Controversy Saying Cardano (ADA) Is “Clearly Superior” to EOS",
      "link": "NULL",
      "pubDate": "2019-11-15T21:00:08.000Z",
      "source": "Historical",
      "sourceKey": "historical",
      "category": "altcoin",
      "currencies": [
        "ADA",
        "EOS"
      ],
      "votes": {
        "positive": 3,
        "negative": 0
      },
      "sentiment": "bullish"
    },
    {
      "title": "Verge surge as PayPal bans Pornhub payments",
      "link": "NULL",
      "pubDate": "2019-11-15T12:11:48.000Z",
      "source": "Historical",
      "sourceKey": "historical",
      "category": "trading",
      "currencies": [
        "XVG"
      ],
      "votes": {
        "positive": 6,
        "negative": 0
      },
      "sentiment": "bullish"
    },
    {
      "title": "“In fact, technology has been the story of human progress from as long back as we know. In 100 years people will lo…",
      "link": "NULL",
      "pubDate": "2019-11-15T12:01:52.000Z",
      "source": "Historical",
      "sourceKey": "historical",
      "category": "general",
      "currencies": [
        "DEEP"
      ]
    },
    {
      "title": "Onepage fully describes ZEON Network for potential partners, exchanges, users of crypto loans and deposits. Review…",
      "link": "NULL",
      "pubDate": "2019-11-15T09:12:25.000Z",
      "source": "Historical",
      "sourceKey": "historical",
      "category": "exchange",
      "currencies": [
        "ZEON"
      ]
    },
    {
      "title": "Humanscape selected as 9th ‘1Q Agile Lab’ member of KEB Hana Bank, the very first accelerator program in Korea…",
      "link": "NULL",
      "pubDate": "2019-11-15T08:47:36.000Z",
      "source": "Historical",
      "sourceKey": "historical",
      "category": "regulation",
      "currencies": [
        "HUM"
      ]
    }
  ]
}